AUTHORS
LICENSE
MANIFEST.in
README.rst
setup.py
pyjade/__init__.py
pyjade/compiler.py
pyjade/convert.py
pyjade/exceptions.py
pyjade/filters.py
pyjade/lexer.py
pyjade/nodes.py
pyjade/parser.py
pyjade/runtime.py
pyjade/utils.py
pyjade.egg-info/PKG-INFO
pyjade.egg-info/SOURCES.txt
pyjade.egg-info/dependency_links.txt
pyjade.egg-info/entry_points.txt
pyjade.egg-info/top_level.txt
pyjade/ext/__init__.py
pyjade/ext/html.py
pyjade/ext/jinja.py
pyjade/ext/mako.py
pyjade/ext/underscore.py
pyjade/ext/django/__init__.py
pyjade/ext/django/compiler.py
pyjade/ext/django/loader.py
pyjade/ext/django/templatetags.py
pyjade/ext/pyramid/__init__.py
pyjade/ext/tornado/__init__.py