Metadata-Version: 1.0
Name: pyjade
Version: 2.0.1
Summary: Jade syntax template adapter for Django, Jinja2, Mako and Tornado templates
Home-page: http://github.com/syrusakbary/pyjade
Author: Syrus Akbary
Author-email: me@syrusakbary.com
License: MIT
Download-URL: git@github.com:syrusakbary/pyjade.git
Keywords: jade template converter
Platform: UNKNOWN
